{"components_avatar_index.md":"CTsOsqqm","components_button-3d_index.md":"DLUdOgAy","components_button_index.md":"CK9Uoaio","components_calendar_index.md":"DOmSkOvp","components_card_index.md":"CAmeqbMG","components_check-box_index.md":"CxpR_eD6","components_divider_index.md":"B4gnTClH","components_popover_index.md":"C_Ntdt-g","components_radio_index.md":"BBPgMKO-","components_rate_index.md":"D0rAT1WW","components_status_index.md":"MDm8l-Al","components_tabs_index.md":"DjAVDTKr","components_tooltip_index.md":"C89fq_Fv","components_tree_index.md":"B1V8kXdb","index.md":"DnRdI9cj","introduce.md":"CpjtORHT","team.md":"CvrnjZey"}
