{"components_affix_index.md":"C2zrNqD7","components_alert_index.md":"B8kwpVao","components_anchor_index.md":"BY4VlROu","components_auto-complete_index.md":"vtVVQ-Eu","components_avatar_index.md":"C7nFmDT0","components_badge-ribbon_index.md":"B_j8luCA","components_badge_index.md":"wm6wEBh9","components_border-beam_index.md":"BdGK9yaz","components_breadcrumb_index.md":"BjQFpdpO","components_button-3d_index.md":"B0Ih2oB0","components_button_index.md":"DZ6Q_RY0","components_calendar_index.md":"rvf9f6H8","components_card-meta_index.md":"B2MQUnya","components_card_index.md":"C1RbyJS7","components_carousel_index.md":"B-4T7uEd","components_cascader_index.md":"CizSTM-k","components_check-box_index.md":"B9YjCyYv","components_checkable-tag_index.md":"CVJmdNdl","components_collapse_index.md":"Be9SUIm5","components_color-picker_index.md":"DmZlu9pS","components_config-provider_index.md":"CJ8DRVXG","components_date-picker_index.md":"NHC7Al8v","components_descriptions_index.md":"BwF_41nh","components_divider_index.md":"crOQrPeC","components_drawer_index.md":"CFrE0SKg","components_dropdown_index.md":"CdLpWQVe","components_empty_index.md":"Ceu6F8ZL","components_flex_index.md":"hJMYeNXq","components_float-button_index.md":"BpwYTTf9","components_form_index.md":"DGEIKdEA","components_grid_index.md":"BlkAxvT8","components_icon_index.md":"DPrDkK8j","components_image-preview_index.md":"0mGhYqC7","components_image_index.md":"BMcDJ50R","components_input-number_index.md":"BENKXaU3","components_input-otp_index.md":"695Ecoq1","components_input-search_index.md":"BoMfmC67","components_input_index.md":"B3rNzXEJ","components_layout_index.md":"zfI-B7H6","components_masonry_index.md":"BDi1dHvA","components_mentions_index.md":"GVI-gqtr","components_menu_index.md":"DdWGicHk","components_message_index.md":"DBd9yhWt","components_modal_index.md":"FKrub47k","components_notification_index.md":"EDiaKLSR","components_pagination_index.md":"bPTF9Ohl","components_popconfirm_index.md":"DCw1L3KD","components_popover_index.md":"5pcpbUrT","components_progress_index.md":"nLt_U-cu","components_radio_index.md":"CHyDFeIn","components_range-picker_index.md":"DoElujed","components_rate_index.md":"DdefSLit","components_result_index.md":"RxOliHb8","components_segmented_index.md":"B0V0yXxG","components_select_index.md":"Do3614Uh","components_skeleton-node_index.md":"BGiD8u07","components_skeleton_index.md":"Cr5rUqvb","components_slider_index.md":"DEoNMcru","components_space-compact_index.md":"jgMynOxA","components_space_index.md":"BfMkr8EG","components_spin_index.md":"CXnn7L3H","components_splitter_index.md":"D5j5f3ai","components_steps_index.md":"Dzzvx6XE","components_switch_index.md":"BXwaNbNl","components_table-column-group_index.md":"C-9QF_Iu","components_table-column_index.md":"6CTWGKnY","components_table-summary_index.md":"Dvr5X8Qr","components_table_index.md":"hpDMK4uZ","components_tabs_index.md":"DJl_ylaF","components_tag_index.md":"CQV70FW4","components_textarea_index.md":"CHXfa705","components_time-picker_index.md":"BZlutmiw","components_time-range-picker_index.md":"BYITpdpS","components_timeline_index.md":"u6DvXGeG","components_tooltip_index.md":"D1QETrG3","components_transfer_index.md":"DEkEFG8P","components_tree-select_index.md":"CTiap_hq","components_tree_index.md":"CKeOc2w9","components_typography_index.md":"DHobrdYX","components_upload_index.md":"Djw2MfO0","components_util_index.md":"CmqGlw-e","components_watermark_index.md":"5Op5ybUD","for-ai.md":"U9fi5a9J","index.md":"DzoXhUzg","introduce.md":"CRCDPURP","quick-start.md":"vSk4NwN-","team.md":"eMgaiMZb"}
