{"components_avatar_index.md":"B9JfZWes","components_button-3d_index.md":"EPlOMzVQ","components_button_index.md":"C2Two7CM","components_calendar_index.md":"B-QA3iCb","components_card_index.md":"CHCXV-lG","components_check-box_index.md":"BbIt38EK","components_divider_index.md":"DNx_st8E","components_input-number_index.md":"CV47xFLM","components_input_index.md":"DRlEvpUr","components_popover_index.md":"Blajrjhm","components_radio_index.md":"DKVKPGR4","components_rate_index.md":"1l_D8CGR","components_slider_index.md":"_xvRLJ7T","components_status_index.md":"ClQHKpue","components_tabs_index.md":"DH924UQm","components_timeline_index.md":"CXkSEpEn","components_tooltip_index.md":"DcbKW3Fl","components_tree_index.md":"Bbe-eB0K","index.md":"DEeFTK_-","introduce.md":"KNnSF7Pg","team.md":"Czmy4jj8"}
