{"components_avatar_index.md":"9761a113","components_button_index.md":"82546db0","components_calendar_index.md":"fdcb3959","components_card_index.md":"f09a033b","components_check-box_index.md":"d72b0439","components_divider_index.md":"fe0df415","components_radio_index.md":"f72fad6d","components_rate_index.md":"7da4f017","components_status_index.md":"32bccbe2","components_tabs_index.md":"7977c3e4","components_tree_index.md":"b2b3ddde","index.md":"d8222364","introduce.md":"9896c19a","team.md":"975a3d61"}
